odoo/addons/shipment_advice_planner_toursolver/README.rst
odoo/addons/shipment_advice_planner_toursolver/__init__.py
odoo/addons/shipment_advice_planner_toursolver/__manifest__.py
odoo/addons/shipment_advice_planner_toursolver/data/ir_cron.xml
odoo/addons/shipment_advice_planner_toursolver/data/ir_sequence.xml
odoo/addons/shipment_advice_planner_toursolver/data/ir_ui_menu.xml
odoo/addons/shipment_advice_planner_toursolver/data/toursolver_backend.xml
odoo/addons/shipment_advice_planner_toursolver/demo/res_compnay.xml
odoo/addons/shipment_advice_planner_toursolver/demo/toursolver_backend.xml
odoo/addons/shipment_advice_planner_toursolver/demo/toursolver_resource.xml
odoo/addons/shipment_advice_planner_toursolver/i18n/es.po
odoo/addons/shipment_advice_planner_toursolver/i18n/fr.po
odoo/addons/shipment_advice_planner_toursolver/i18n/it.po
odoo/addons/shipment_advice_planner_toursolver/i18n/shipment_advice_planner_toursolver.pot
odoo/addons/shipment_advice_planner_toursolver/migrations/16.0.3.0.0/pre-migrate.py
odoo/addons/shipment_advice_planner_toursolver/migrations/16.0.3.0.1/pre-migrate.py
odoo/addons/shipment_advice_planner_toursolver/models/__init__.py
odoo/addons/shipment_advice_planner_toursolver/models/res_company.py
odoo/addons/shipment_advice_planner_toursolver/models/res_config_settings.py
odoo/addons/shipment_advice_planner_toursolver/models/res_partner.py
odoo/addons/shipment_advice_planner_toursolver/models/shipment_advice.py
odoo/addons/shipment_advice_planner_toursolver/models/stock_picking.py
odoo/addons/shipment_advice_planner_toursolver/models/tools.py
odoo/addons/shipment_advice_planner_toursolver/models/toursolver_backend.py
odoo/addons/shipment_advice_planner_toursolver/models/toursolver_delivery_window.py
odoo/addons/shipment_advice_planner_toursolver/models/toursolver_request_props_definition.py
odoo/addons/shipment_advice_planner_toursolver/models/toursolver_resource.py
odoo/addons/shipment_advice_planner_toursolver/models/toursolver_task.py
odoo_addon_shipment_advice_planner_toursolver-16.0.3.1.0.2.dist-info/METADATA
odoo_addon_shipment_advice_planner_toursolver-16.0.3.1.0.2.dist-info/WHEEL
odoo_addon_shipment_advice_planner_toursolver-16.0.3.1.0.2.dist-info/top_level.txt
odoo_addon_shipment_advice_planner_toursolver-16.0.3.1.0.2.dist-info/RECORD
