Metadata-Version: 2.1
Name: odoo-addon-shipment_advice_planner_toursolver
Version: 16.0.3.1.0.2
Summary: Shipment advices planning by geo-optimization (TourSolver)
Home-page: https://github.com/OCA/stock-logistics-transport
Author: ACSONE SA/NV,Odoo Community Association (OCA)
Author-email: support@odoo-community.org
License: AGPL-3
Classifier: Programming Language :: Python
Classifier: Framework :: Odoo
Classifier: Framework :: Odoo :: 16.0
Classifier: License :: OSI Approved :: GNU Affero General Public License v3
Requires-Python: >=3.10
Requires-Dist: odoo-addon-base-time-window<16.1dev,>=16.0dev
Requires-Dist: odoo-addon-shipment-advice-planner<16.1dev,>=16.0dev
Requires-Dist: odoo<16.1dev,>=16.0a
